tailflow/__init__.py
tailflow/cli.py
tailflow-0.1.1.dist-info/METADATA
tailflow-0.1.1.dist-info/WHEEL
tailflow-0.1.1.dist-info/entry_points.txt
tailflow-0.1.1.dist-info/RECORD
